collective.externallinkfilter-2.0-py3.11-nspkg.pth
collective/externallinkfilter/__init__.py
collective/externallinkfilter/configure.zcml
collective/externallinkfilter/interfaces.py
collective/externallinkfilter/overrides.zcml
collective/externallinkfilter/resolveuid_and_caption.py
collective/externallinkfilter/testing.py
collective/externallinkfilter/tests/__init__.py
collective/externallinkfilter/tests/test_setup.py
collective_externallinkfilter-2.0.dist-info/licenses/LICENSE.GPL
collective_externallinkfilter-2.0.dist-info/licenses/LICENSE.rst
collective_externallinkfilter-2.0.dist-info/METADATA
collective_externallinkfilter-2.0.dist-info/WHEEL
collective_externallinkfilter-2.0.dist-info/entry_points.txt
collective_externallinkfilter-2.0.dist-info/namespace_packages.txt
collective_externallinkfilter-2.0.dist-info/top_level.txt
collective_externallinkfilter-2.0.dist-info/RECORD
